etcd3_wrapper/__init__.py
etcd3_wrapper/etcd3_wrapper.py
etcd3_wrapper/etcd_wrapper.py
etcd3_wrapper-0.5.4.dist-info/LICENSE
etcd3_wrapper-0.5.4.dist-info/METADATA
etcd3_wrapper-0.5.4.dist-info/WHEEL
etcd3_wrapper-0.5.4.dist-info/top_level.txt
etcd3_wrapper-0.5.4.dist-info/RECORD
