Metadata-Version: 2.1
Name: etcd3-wrapper
Version: 0.5.4
Summary: A wrapper around etcd3 package
Home-page: https://code.ungleich.ch/ungleich-public/etcd3_wrapper
Author: ungleich
Author-email: hacking@ungleich.ch
License: UNKNOWN
Platform: UNKNOWN
Classifier: Programming Language :: Python :: 3
Requires-Python: >=3.5
Requires-Dist: etcd3
